binaryiotools/__init__.py
binaryiotools-2021.0.3.dist-info/LICENSE.txt
binaryiotools-2021.0.3.dist-info/WHEEL
binaryiotools-2021.0.3.dist-info/METADATA
binaryiotools-2021.0.3.dist-info/RECORD
