Metadata-Version: 2.1
Name: binaryiotools
Version: 2021.0.3
Summary: Does boilerplate things like reading the next uint32 from a file or binary stream
Home-page: https://github.com/FHPythonUtils/BinaryIOTools
License: LGPL-3.0-only
Author: FredHappyface
Requires-Python: >=3.7,<4.0
Classifier: Development Status :: 5 - Production/Stable
Classifier: Intended Audience :: Developers
Classifier: Intended Audience :: Education
Classifier: License :: OSI Approved :: GNU Lesser General Public License v3 (LGPLv3)
Classifier: Natural Language :: English
Classifier: Operating System :: OS Independent
Classifier: Programming Language :: Python :: 3
Classifier: Programming Language :: Python :: 3.10
Classifier: Programming Language :: Python :: 3.7
Classifier: Programming Language :: Python :: 3.8
Classifier: Programming Language :: Python :: 3.9
Classifier: Programming Language :: Python :: Implementation :: CPython
Classifier: Topic :: Software Development :: Libraries :: Python Modules
Classifier: Topic :: Utilities
Project-URL: Documentation, https://github.com/FHPythonUtils/BinaryIOTools/blob/master/README.md
Project-URL: Repository, https://github.com/FHPythonUtils/BinaryIOTools
